[{"id":1,"titol":"Stewart Lee: If You Prefer a Milder Comedian, Please Ask for One","descripcio":"Inj musc/fasc/tend at forearm level, right arm, sequela","disponibilitat":true},
{"id":2,"titol":"Lady with the Dog, The (Dama s sobachkoy)","descripcio":"Mechanical entropion of right lower eyelid","disponibilitat":true},
{"id":3,"titol":"Private Parts","descripcio":"Drug/chem diabetes mellitus w neurological complications","disponibilitat":false},
{"id":4,"titol":"Legion","descripcio":"Traumatic shock, initial encounter","disponibilitat":true},
{"id":5,"titol":"We Are What We Are","descripcio":"Unsp adverse effect of drug or medicament, subs encntr","disponibilitat":true},
{"id":6,"titol":"First Grader, The","descripcio":"Frostbite with tissue necrosis of unspecified wrist, sequela","disponibilitat":true},
{"id":7,"titol":"Mirror Has Two Faces, The","descripcio":"Congenital malformation of great vein, unspecified","disponibilitat":false},
{"id":8,"titol":"Lookin' to Get Out","descripcio":"Other skateboard accident, initial encounter","disponibilitat":false},
{"id":9,"titol":"Johnny Mad Dog","descripcio":"Laceration of gallbladder, initial encounter","disponibilitat":false},
{"id":10,"titol":"Super Cops, The","descripcio":"Laceration of musc/tend the rotator cuff of right shoulder","disponibilitat":true},
{"id":11,"titol":"Fan, The","descripcio":"Avulsion of left eye","disponibilitat":true},
{"id":12,"titol":"Vacancy 2: The First Cut","descripcio":"Poisoning by mineralocorticoids and their antag, accidental","disponibilitat":true},
{"id":13,"titol":"Silmido","descripcio":"Unsp injury of musc/fasc/tend at wrs/hnd lv, left hand","disponibilitat":false},
{"id":14,"titol":"Peace, Love & Misunderstanding","descripcio":"Drug induced tics and other tics of organic origin","disponibilitat":false},
{"id":15,"titol":"Let My Puppets Come","descripcio":"Dislocation of L2/L3 lumbar vertebra, subsequent encounter","disponibilitat":false},
{"id":16,"titol":"Age of Dinosaurs","descripcio":"Poisoning by smallpox vaccines, intentional self-harm","disponibilitat":false},
{"id":17,"titol":"Time to Die (Tiempo de morir)","descripcio":"Pathological fracture, left foot, subs for fx w nonunion","disponibilitat":false},
{"id":18,"titol":"Odd Thomas","descripcio":"Non-in-line roller-skater colliding w statnry obj, subs","disponibilitat":true},
{"id":19,"titol":"Vertical Features Remake","descripcio":"Multiple fx of ribs, unsp side, subs for fx w delay heal","disponibilitat":true},
{"id":20,"titol":"Hoodwinked!","descripcio":"Intentional self-harm by hot household appliances, init","disponibilitat":true},
{"id":21,"titol":"Knights of Bloodsteel","descripcio":"Psoriatic spondylitis","disponibilitat":false},
{"id":22,"titol":"Pure Country","descripcio":"Multiple fractures of pelvis w stable disrupt of pelvic ring","disponibilitat":true},
{"id":23,"titol":"Creep Van","descripcio":"Reiter's disease, right ankle and foot","disponibilitat":true},
{"id":24,"titol":"Tales of Vesperia: The First Strike (Teiruzu obu vesuperia: The first strike)","descripcio":"Post-traumatic headache","disponibilitat":true},
{"id":25,"titol":"Clubbed","descripcio":"Disp fx of anterior column of right acetab, init for opn fx","disponibilitat":false},
{"id":26,"titol":"Streaks, The (Pregi)","descripcio":"Drug-induced chronic gout, left ankle and foot","disponibilitat":false},
{"id":27,"titol":"Head On","descripcio":"Encounter for attention to artificial vagina","disponibilitat":true},
{"id":28,"titol":"Young Tom Edison","descripcio":"Corrosions involving 30-39% of body surface","disponibilitat":false},
{"id":29,"titol":"Unforgiven, The","descripcio":"Maternal care for oth rhesus isoimmun, third tri, fetus 4","disponibilitat":true},
{"id":30,"titol":"Art of Crying, The (Kunsten at græde i kor)","descripcio":"Underdosing of agents primarily acting on the resp sys","disponibilitat":true},
{"id":31,"titol":"Big Squeeze, The","descripcio":"Poisoning by oth anti-cmn-cold drugs, accidental","disponibilitat":true},
{"id":32,"titol":"Plot Against Harry, The","descripcio":"Poisoning by glucocort/synth analog, assault, subs","disponibilitat":true},
{"id":33,"titol":"Solarbabies","descripcio":"Legal intervnt involving injury by dynamite, suspect injured","disponibilitat":true},
{"id":34,"titol":"Being There","descripcio":"Laceration with foreign body, unspecified ankle, sequela","disponibilitat":false},
{"id":35,"titol":"Creeping Flesh, The","descripcio":"Contusion of left upper arm, initial encounter","disponibilitat":false},
{"id":36,"titol":"Grace of Monaco","descripcio":"Traumatic rupture of unspecified radiocarpal ligament","disponibilitat":true},
{"id":37,"titol":"Asterix and the Vikings (Astérix et les Vikings)","descripcio":"Spacecraft fire injuring occupant, sequela","disponibilitat":false},
{"id":38,"titol":"Reykjavik Whale Watching Massacre","descripcio":"Open bite, right thigh","disponibilitat":false},
{"id":39,"titol":"Sione's Wedding (Samoan Wedding)","descripcio":"Cutaneous abscess of right foot","disponibilitat":true},
{"id":40,"titol":"Prisoner of Shark Island, The","descripcio":"Pnctr w fb of abd wall, unsp quadrant w penet perit cav","disponibilitat":true},
{"id":41,"titol":"Loneliest Planet, The","descripcio":"Primary dysmenorrhea","disponibilitat":false},
{"id":42,"titol":"Assembly (Ji jie hao) ","descripcio":"Inj intrinsic msl/tnd at ankle and foot level, left foot","disponibilitat":false},
{"id":43,"titol":"They Shoot Horses, Don't They?","descripcio":"Oth injury due to other accident to passenger ship, sequela","disponibilitat":false},
{"id":44,"titol":"Just Another Love Story (Kærlighed på film)","descripcio":"Unspecified open wound, unspecified thigh","disponibilitat":true},
{"id":45,"titol":"Black Friday","descripcio":"Corros third degree of unsp mult fingers (nail), inc thumb","disponibilitat":true},
{"id":46,"titol":"Man Apart, A","descripcio":"War op w dest arcrft due to enmy fire/expls, milt, init","disponibilitat":false},
{"id":47,"titol":"Jew Süss (Jud Süß)","descripcio":"Traumatic rupture of left ulnar collateral ligament","disponibilitat":true},
{"id":48,"titol":"Rage in Harlem, A","descripcio":"Villonodular synovitis (pigmented), left hip","disponibilitat":true},
{"id":49,"titol":"Tom and Jerry: A Nutcracker Tale","descripcio":"Lac w/o fb of low back and pelvis w penet retroperiton, init","disponibilitat":false},
{"id":50,"titol":"Deaths of Ian Stone, The","descripcio":"Infect/inflm reaction due to oth internal prosth dev/grft","disponibilitat":false},
{"id":51,"titol":"Last Action Hero","descripcio":"Contact with other nonpowered hand tool, initial encounter","disponibilitat":false},
{"id":52,"titol":"Haunted Palace, The","descripcio":"Lac w fb of l bk wl of thorax w penet thoracic cavity, subs","disponibilitat":true},
{"id":53,"titol":"Caretakers, The","descripcio":"Open bite of r frnt wl of thorax w/o penet thor cavity, init","disponibilitat":true},
{"id":54,"titol":"Invasion of Astro-Monster (Godzilla vs. Monster Zero) (Kaijû daisensô)","descripcio":"Person outside car injured in clsn w nonmtr vehicle nontraf","disponibilitat":false},
{"id":55,"titol":"Drifting Clouds (Kauas pilvet karkaavat)","descripcio":"Assault by machine gun, sequela","disponibilitat":true},
{"id":56,"titol":"Spellbound","descripcio":"Unsp pedl cyclst injured in collision w oth pedl cyc nontraf","disponibilitat":false},
{"id":57,"titol":"Casualties of War","descripcio":"Ped on foot inj in clsn w nonmtr vehicle in traf, sequela","disponibilitat":true},
{"id":58,"titol":"Mid-August Lunch (Pranzo di ferragosto)","descripcio":"Laceration w fb of l bk wl of thorax w penet thoracic cavity","disponibilitat":true},
{"id":59,"titol":"Tribe, The (Plemya)","descripcio":"Heat exposure on board unspecified watercraft, subs encntr","disponibilitat":false},
{"id":60,"titol":"Creature with the Atom Brain","descripcio":"Blood alcohol level of less than 20 mg/100 ml","disponibilitat":false},
{"id":61,"titol":"Croods, The","descripcio":"Complete lesion at unspecified level of cervical spinal cord","disponibilitat":true},
{"id":62,"titol":"President's Analyst, The","descripcio":"Fracture of unspecified part of body of left mandible, 7thB","disponibilitat":false},
{"id":63,"titol":"In the Cut","descripcio":"Delayed or excessive hemor following incmpl spon abortion","disponibilitat":false},
{"id":64,"titol":"Grey Zone, The","descripcio":"Disp fx of olecran pro w/o intartic extn unsp ulna, 7thP","disponibilitat":false},
{"id":65,"titol":"Medium Cool","descripcio":"Verteb art compression syndromes, occipt-atlan-ax region","disponibilitat":true},
{"id":66,"titol":"Sleepwalk with Me","descripcio":"Nondisp seg fx shaft of ulna, unsp arm, 7thP","disponibilitat":false},
{"id":67,"titol":"Great Day in the Morning","descripcio":"Self-harm by jumping or lying in front of mtr veh, sequela","disponibilitat":false},
{"id":68,"titol":"Agenda: Grinding America Down","descripcio":"Wear of artic bearing surface of int prosth r hip jt, subs","disponibilitat":false},
{"id":69,"titol":"Spiders, Part 2: The Diamond Ship, The (Die Spinnen, 2. Teil - Das Brillantenschiff)","descripcio":"Displ avuls fx (chip fracture) of l talus, 7thD","disponibilitat":true},
{"id":70,"titol":"Carry On, Constable","descripcio":"Prsn brd/alit hv veh injured pick-up truck, pk-up/van, subs","disponibilitat":false},
{"id":71,"titol":"Animal Kingdom","descripcio":"Abn lev drug/meds/biol subst in specmn fr dgstv org/abd cav","disponibilitat":false},
{"id":72,"titol":"Other One, The","descripcio":"Open bite of unsp external genital organs, male, subs encntr","disponibilitat":false},
{"id":73,"titol":"American Haunting, An","descripcio":"Subluxation of unsp interphaln joint of r rng fngr, sequela","disponibilitat":true},
{"id":74,"titol":"Begone Dull Care","descripcio":"Nondisp longitud fx unsp patella, 7thD","disponibilitat":false},
{"id":75,"titol":"Ill Manors","descripcio":"External constriction of hand","disponibilitat":false},
{"id":76,"titol":"Dark Journey","descripcio":"Sltr-haris Type I physl fx low end r tibia, 7thP","disponibilitat":true},
{"id":77,"titol":"F.I.S.T.","descripcio":"Adverse effect of other nonsteroidal anti-inflammatory drugs","disponibilitat":false},
{"id":78,"titol":"Crime Wave","descripcio":"Corrosion of second degree of lip(s), subsequent encounter","disponibilitat":true},
{"id":79,"titol":"Promise Me This (Zavet)","descripcio":"Contusion of eyeball and orbital tissues, unsp eye, sequela","disponibilitat":true},
{"id":80,"titol":"See What I'm Saying: The Deaf Entertainers Documentary","descripcio":"Fracture of oth skull and facial bones, right side, init","disponibilitat":false},
{"id":81,"titol":"The Reunion","descripcio":"Displaced osteochondral fracture of left patella","disponibilitat":false},
{"id":82,"titol":"King of Germany","descripcio":"Bunion","disponibilitat":false},
{"id":83,"titol":"Bounty, The","descripcio":"Lacrimal gland dislocation, left lacrimal gland","disponibilitat":false},
{"id":84,"titol":"12 Rounds","descripcio":"Underdosing of antihyperlip and antiarterio drugs, subs","disponibilitat":false},
{"id":85,"titol":"Airplane!","descripcio":"Slip/trip w/o fall due to step into hole or opening, sequela","disponibilitat":true},
{"id":86,"titol":"Palmetto","descripcio":"Other assault by crashing of motor vehicle, sequela","disponibilitat":false},
{"id":87,"titol":"In the Winter Dark","descripcio":"Abnormal immunological finding in serum, unspecified","disponibilitat":false},
{"id":88,"titol":"Asphalt Playground (La cité rose)","descripcio":"Stress fracture, right ulna, subs for fx w routn heal","disponibilitat":true},
{"id":89,"titol":"The Return of Ringo","descripcio":"Driver of oth sp off-rd mv injured in traffic accident, init","disponibilitat":true},
{"id":90,"titol":"Guardian, The","descripcio":"Poisoning by drugs aff uric acid metab, self-harm, sequela","disponibilitat":false},
{"id":91,"titol":"St. Francisville Experiment, The","descripcio":"Postproc hematoma and seroma of a GU sys org fol a procedure","disponibilitat":false},
{"id":92,"titol":"Man from Earth, The","descripcio":"Adverse effect of amphetamines, sequela","disponibilitat":true},
{"id":93,"titol":"Himalaya (Himalaya - l'enfance d'un chef)","descripcio":"Injury of other specified nerves of neck, sequela","disponibilitat":false},
{"id":94,"titol":"Je préfère qu'on reste amis","descripcio":"Unsp injury of anterior tibial artery, unspecified leg","disponibilitat":true},
{"id":95,"titol":"Pride and Prejudice","descripcio":"Unspecified injury of left kidney, initial encounter","disponibilitat":false},
{"id":96,"titol":"Nature Calls","descripcio":"Laceration with foreign body of unsp buttock, init encntr","disponibilitat":false},
{"id":97,"titol":"Love Me If You Dare (Jeux d'enfants)","descripcio":"Unsp bus occupant injured in clsn w oth mv in traf, init","disponibilitat":false},
{"id":98,"titol":"Mouse That Roared, The","descripcio":"Rheumatoid polyneurop w rheumatoid arthritis of right knee","disponibilitat":false},
{"id":99,"titol":"De-Lovely","descripcio":"Toxic maculopathy, right eye","disponibilitat":true},
{"id":100,"titol":"Innocence","descripcio":"Unsp car occ injured in clsn w nonmtr vehicle nontraf, subs","disponibilitat":false}]